AUTHORS
CHANGES
LICENSE
MANIFEST.in
README.md
setup.py
bin/pdf_collate
pdf_collate/__init__.py
pdf_collate/pdf.py
pdf_collate/version.py
py_pdf_collate.egg-info/PKG-INFO
py_pdf_collate.egg-info/SOURCES.txt
py_pdf_collate.egg-info/dependency_links.txt
py_pdf_collate.egg-info/requires.txt
py_pdf_collate.egg-info/top_level.txt