Metadata-Version: 1.0
Name: py-pdf-collate
Version: 0.1.1
Summary: A python script that collates your PDF documents.
Home-page: https://github.com/mattkoskela/py-pdf-collate
Author: Matt Koskela
Author-email: mattkoskela@gmail.com
License: LICENSE
Platform: UNKNOWN
